mcp_rocq/__init__.py
mcp_rocq/__main__.py
mcp_rocq/cli.py
mcp_rocq/patch.py
mcp_rocq/server.py
mcp_rocq/handlers/__init__.py
mcp_rocq/handlers/coq_session.py
mcp_rocq/handlers/inductive_types.py
mcp_rocq/handlers/prover.py
mcp_rocq/handlers/type_checker.py
mcp_rocq/parsers/xml_parser.py
iflow_mcp_angrysky56_mcp_rocq-0.1.0.dist-info/METADATA
iflow_mcp_angrysky56_mcp_rocq-0.1.0.dist-info/WHEEL
iflow_mcp_angrysky56_mcp_rocq-0.1.0.dist-info/entry_points.txt
iflow_mcp_angrysky56_mcp_rocq-0.1.0.dist-info/licenses/LICENSE
iflow_mcp_angrysky56_mcp_rocq-0.1.0.dist-info/RECORD
